clife_svc/__init__.py
clife_svc/application.py
clife_svc/config/__init__.py
clife_svc/config/configmap.py
clife_svc/config/disconf.py
clife_svc/errors/__init__.py
clife_svc/errors/error_code.py
clife_svc/libs/__init__.py
clife_svc/libs/context.py
clife_svc/libs/http_request.py
clife_svc/libs/log.py
clife_svc/libs/mq_handler.py
clife_svc/libs/utils.py
clife_svc2-2.0.0.dist-info/METADATA
clife_svc2-2.0.0.dist-info/WHEEL
clife_svc2-2.0.0.dist-info/top_level.txt
clife_svc2-2.0.0.dist-info/RECORD
